MANIFEST.in
setup.cfg
setup.py
stratus_api/events/__init__.py
stratus_api/events/events.py
stratus_api/events/pubsub.py
stratus_api_events.egg-info/PKG-INFO
stratus_api_events.egg-info/SOURCES.txt
stratus_api_events.egg-info/dependency_links.txt
stratus_api_events.egg-info/requires.txt
stratus_api_events.egg-info/top_level.txt