Metadata-Version: 2.1
Name: stratus-api-events
Version: 0.0.7
Summary: Streamlined Pubsub Events
Home-page: https://bitbucket.org/adarainc/stratus-api-events
Author: DOT
Author-email: dot@adara.com
Classifier: Programming Language :: Python :: 3
Classifier: License :: OSI Approved :: MIT License
Classifier: Operating System :: OS Independent
Requires-Python: >=3.11
